{"v":"5.5.8","fr":60,"ip":0,"op":420,"w":491,"h":402,"nm":"Animacion_carro","ddd":0,"assets":[],"layers":[{"ddd":0,"ind":1,"ty":4,"nm":"pista contornos","sr":1,"ks":{"o":{"a":1,"k":[{"i":{"x":[0.833],"y":[0.833]},"o":{"x":[0.167],"y":[0.167]},"t":0,"s":[0]},{"t":57,"s":[71]}],"ix":11},"r":{"a":0,"k":0,"ix":10},"p":{"a":1,"k":[{"i":{"x":0.833,"y":0.833},"o":{"x":0.167,"y":0.167},"t":0,"s":[732.5,297,0],"to":[-80.667,0,0],"ti":[80.667,0,0]},{"t":56,"s":[248.5,297,0]}],"ix":2},"a":{"a":0,"k":[282,256,0],"ix":1},"s":{"a":0,"k":[67,67,100],"ix":6}},"ao":0,"shapes":[{"ty":"gr","it":[{"ind":0,"ty":"sh","ix":1,"ks":{"a":0,"k":{"i":[[0,0],[0,0]],"o":[[0,0],[0,0]],"v":[[35.261,255.91],[543.514,255.91]],"c":false},"ix":2},"nm":"Trazado 1","mn":"ADBE Vector Shape - Group","hd":false},{"ty":"st","c":{"a":0,"k":[0.866999966491,0.866999966491,0.866999966491,1],"ix":3},"o":{"a":0,"k":100,"ix":4},"w":{"a":0,"k":8,"ix":5},"lc":2,"lj":1,"ml":10,"bm":0,"nm":"Trazo 1","mn":"ADBE Vector Graphic - Stroke","hd":false},{"ty":"tr","p":{"a":0,"k":[0,0],"ix":2},"a":{"a":0,"k":[0,0],"ix":1},"s":{"a":0,"k":[100,100],"ix":3},"r":{"a":0,"k":0,"ix":6},"o":{"a":0,"k":100,"ix":7},"sk":{"a":0,"k":0,"ix":4},"sa":{"a":0,"k":0,"ix":5},"nm":"Transformar"}],"nm":"Grupo 1","np":2,"cix":2,"bm":0,"ix":1,"mn":"ADBE Vector Group","hd":false}],"ip":0,"op":420,"st":0,"bm":0},{"ddd":0,"ind":3,"ty":4,"nm":"rueda 1 contornos","sr":1,"ks":{"o":{"a":0,"k":100,"ix":11},"r":{"a":1,"k":[{"i":{"x":[0.833],"y":[0.833]},"o":{"x":[0.167],"y":[0.167]},"t":0,"s":[0]},{"i":{"x":[0.833],"y":[0.833]},"o":{"x":[0.167],"y":[0.167]},"t":163,"s":[-1470]},{"t":415,"s":[-2550]}],"ix":10},"p":{"a":1,"k":[{"i":{"x":0.833,"y":0.833},"o":{"x":0.167,"y":0.167},"t":0,"s":[572.5,252.99999999999997,0],"to":[-76.833,0,0],"ti":[76.833,0,0]},{"t":56,"s":[111.5,252.99999999999997,0]}],"ix":2},"a":{"a":0,"k":[46,46,0],"ix":1},"s":{"a":0,"k":[87,87,100],"ix":6}},"ao":0,"shapes":[{"ty":"gr","it":[{"ind":0,"ty":"sh","ix":1,"ks":{"a":0,"k":{"i":[[0,-2.305],[2.305,0],[0,2.305],[-2.305,0]],"o":[[0,2.305],[-2.305,0],[0,-2.305],[2.305,0]],"v":[[4.173,0.001],[0,4.174],[-4.173,0.001],[0,-4.174]],"c":true},"ix":2},"nm":"Trazado 1","mn":"ADBE Vector Shape - Group","hd":false},{"ty":"fl","c":{"a":0,"k":[0.243000000598,0.263000009574,0.277999997606,1],"ix":4},"o":{"a":0,"k":100,"ix":5},"r":1,"bm":0,"nm":"Relleno 1","mn":"ADBE Vector Graphic - Fill","hd":false},{"ty":"tr","p":{"a":0,"k":[45.625,46.528],"ix":2},"a":{"a":0,"k":[0,0],"ix":1},"s":{"a":0,"k":[100,100],"ix":3},"r":{"a":0,"k":0,"ix":6},"o":{"a":0,"k":100,"ix":7},"sk":{"a":0,"k":0,"ix":4},"sa":{"a":0,"k":0,"ix":5},"nm":"Transformar"}],"nm":"Grupo 1","np":2,"cix":2,"bm":0,"ix":1,"mn":"ADBE Vector Group","hd":false},{"ty":"gr","it":[{"ind":0,"ty":"sh","ix":1,"ks":{"a":0,"k":{"i":[[0.001,-4.901],[0.307,-3.339],[4.556,6.38],[-1.902,-0.183]],"o":[[0,2.182],[-7.776,-2.092],[3.365,-1.696],[2.165,0.209]],"v":[[9.685,-2.629],[9.326,9.51],[-9.686,-3.717],[4.355,-9.327]],"c":true},"ix":2},"nm":"Trazado 1","mn":"ADBE Vector Shape - Group","hd":false},{"ty":"fl","c":{"a":0,"k":[0.243000000598,0.263000009574,0.277999997606,1],"ix":4},"o":{"a":0,"k":100,"ix":5},"r":1,"bm":0,"nm":"Relleno 1","mn":"ADBE Vector Graphic - Fill","hd":false},{"ty":"tr","p":{"a":0,"k":[27.087,69.225],"ix":2},"a":{"a":0,"k":[0,0],"ix":1},"s":{"a":0,"k":[100,100],"ix":3},"r":{"a":0,"k":0,"ix":6},"o":{"a":0,"k":100,"ix":7},"sk":{"a":0,"k":0,"ix":4},"sa":{"a":0,"k":0,"ix":5},"nm":"Transformar"}],"nm":"Grupo 2","np":2,"cix":2,"bm":0,"ix":2,"mn":"ADBE Vector Group","hd":false},{"ty":"gr","it":[{"ind":0,"ty":"sh","ix":1,"ks":{"a":0,"k":{"i":[[-0.678,1.585],[-4.669,-1.49],[-2.784,-1.122],[7.199,-2.427]],"o":[[0.856,-1.999],[1.846,0.589],[-4.17,6.181],[-0.531,-3.846]],"v":[[-8.736,-4.735],[-0.95,-8.084],[9.413,-3.775],[-8.09,9.574]],"c":true},"ix":2},"nm":"Trazado 1","mn":"ADBE Vector Shape - Group","hd":false},{"ty":"fl","c":{"a":0,"k":[0.243000000598,0.263000009574,0.277999997606,1],"ix":4},"o":{"a":0,"k":100,"ix":5},"r":1,"bm":0,"nm":"Relleno 1","mn":"ADBE Vector Graphic - Fill","hd":false},{"ty":"tr","p":{"a":0,"k":[64.406,68.541],"ix":2},"a":{"a":0,"k":[0,0],"ix":1},"s":{"a":0,"k":[100,100],"ix":3},"r":{"a":0,"k":0,"ix":6},"o":{"a":0,"k":100,"ix":7},"sk":{"a":0,"k":0,"ix":4},"sa":{"a":0,"k":0,"ix":5},"nm":"Transformar"}],"nm":"Grupo 3","np":2,"cix":2,"bm":0,"ix":3,"mn":"ADBE Vector Group","hd":false},{"ty":"gr","it":[{"ind":0,"ty":"sh","ix":1,"ks":{"a":0,"k":{"i":[[-2.748,4.044],[-1.934,2.415],[-0.021,-7.812],[1.616,0.308]],"o":[[1.124,-1.655],[4.384,5.758],[-3.783,-0.62],[-3.932,-0.749]],"v":[[-6.087,-1.73],[1.814,-10.383],[8.835,10.383],[-2.972,8.46]],"c":true},"ix":2},"nm":"Trazado 1","mn":"ADBE Vector Shape - Group","hd":false},{"ty":"fl","c":{"a":0,"k":[0.243000000598,0.263000009574,0.277999997606,1],"ix":4},"o":{"a":0,"k":100,"ix":5},"r":1,"bm":0,"nm":"Relleno 1","mn":"ADBE Vector Graphic - Fill","hd":false},{"ty":"tr","p":{"a":0,"k":[70.832,35.113],"ix":2},"a":{"a":0,"k":[0,0],"ix":1},"s":{"a":0,"k":[100,100],"ix":3},"r":{"a":0,"k":0,"ix":6},"o":{"a":0,"k":100,"ix":7},"sk":{"a":0,"k":0,"ix":4},"sa":{"a":0,"k":0,"ix":5},"nm":"Transformar"}],"nm":"Grupo 4","np":2,"cix":2,"bm":0,"ix":4,"mn":"ADBE Vector Group","hd":false},{"ty":"gr","it":[{"ind":0,"ty":"sh","ix":1,"ks":{"a":0,"k":{"i":[[1.373,-0.97],[3.196,3.715],[2.048,2.982],[-4.156,0],[-3.504,-1.207]],"o":[[-1.776,1.254],[-1.561,-1.813],[3.686,-1.352],[3.914,0],[-1.575,3.539]],"v":[[4.979,5.132],[-4.788,4.872],[-11.499,-6.495],[0.326,-8.587],[11.499,-6.717]],"c":true},"ix":2},"nm":"Trazado 1","mn":"ADBE Vector Shape - Group","hd":false},{"ty":"fl","c":{"a":0,"k":[0.243000000598,0.263000009574,0.277999997606,1],"ix":4},"o":{"a":0,"k":100,"ix":5},"r":1,"bm":0,"nm":"Relleno 1","mn":"ADBE Vector Graphic - Fill","hd":false},{"ty":"tr","p":{"a":0,"k":[45.021,19.857],"ix":2},"a":{"a":0,"k":[0,0],"ix":1},"s":{"a":0,"k":[100,100],"ix":3},"r":{"a":0,"k":0,"ix":6},"o":{"a":0,"k":100,"ix":7},"sk":{"a":0,"k":0,"ix":4},"sa":{"a":0,"k":0,"ix":5},"nm":"Transformar"}],"nm":"Grupo 5","np":2,"cix":2,"bm":0,"ix":5,"mn":"ADBE Vector Group","hd":false},{"ty":"gr","it":[{"ind":0,"ty":"sh","ix":1,"ks":{"a":0,"k":{"i":[[4.672,-1.479],[3.108,-0.708],[0,0.284],[-4.314,5.738],[-0.375,-1.749]],"o":[[-1.966,0.623],[-0.007,-0.282],[0,-7.732],[2.666,2.807],[0.456,2.127]],"v":[[3.896,7.859],[-8.548,10.725],[-8.568,9.878],[-1.697,-10.725],[7.495,0.001]],"c":true},"ix":2},"nm":"Trazado 1","mn":"ADBE Vector Shape - Group","hd":false},{"ty":"fl","c":{"a":0,"k":[0.243000000598,0.263000009574,0.277999997606,1],"ix":4},"o":{"a":0,"k":100,"ix":5},"r":1,"bm":0,"nm":"Relleno 1","mn":"ADBE Vector Graphic - Fill","hd":false},{"ty":"tr","p":{"a":0,"k":[19.592,35.715],"ix":2},"a":{"a":0,"k":[0,0],"ix":1},"s":{"a":0,"k":[100,100],"ix":3},"r":{"a":0,"k":0,"ix":6},"o":{"a":0,"k":100,"ix":7},"sk":{"a":0,"k":0,"ix":4},"sa":{"a":0,"k":0,"ix":5},"nm":"Transformar"}],"nm":"Grupo 6","np":2,"cix":2,"bm":0,"ix":6,"mn":"ADBE Vector Group","hd":false},{"ty":"gr","it":[{"ind":0,"ty":"sh","ix":1,"ks":{"a":0,"k":{"i":[[-1.966,0.623],[0.456,2.127],[2.666,2.807],[-6.271,2.302],[-1.561,-1.813],[-1.777,1.255],[-1.575,3.539],[-4.063,-5.298],[1.133,-1.654],[-1.669,-1.394],[-3.812,-0.62],[0,-0.032],[3.693,-5.474],[1.847,0.589],[0.856,-2],[-0.531,-3.846],[3.838,0],[2.85,0.767],[0,2.183],[2.164,0.208],[3.364,-1.696],[0.173,7.103]],"o":[[4.672,-1.479],[-0.375,-1.749],[3.944,-5.247],[2.047,2.981],[3.196,3.715],[1.373,-0.969],[6.439,2.217],[-1.949,2.415],[-2.768,4.044],[1.268,1.059],[0,0.032],[0,7.101],[-2.784,-1.122],[-4.669,-1.489],[-0.678,1.585],[-3.446,1.162],[-3.091,0],[0.307,-3.339],[0.001,-4.9],[-1.902,-0.183],[-3.857,-5.402],[3.108,-0.708]],"v":[[-26.074,-2.374],[-20.453,-12.259],[-27.462,-21.539],[-11.835,-33.167],[-5.621,-25.251],[5.677,-23.966],[11.164,-33.388],[27.237,-21.799],[22.323,-15.13],[23.987,-3.881],[34.31,-1.032],[34.313,-0.936],[28.462,18.237],[20.952,15.564],[10.655,20.39],[10.959,31.586],[-0.011,33.388],[-8.945,32.206],[-8.586,23.111],[-16.31,14.767],[-27.956,18.98],[-34.313,-0.088]],"c":true},"ix":2},"nm":"Trazado 1","mn":"ADBE Vector Shape - Group","hd":false},{"ty":"fl","c":{"a":0,"k":[0.666999966491,0.666999966491,0.666999966491,1],"ix":4},"o":{"a":0,"k":100,"ix":5},"r":1,"bm":0,"nm":"Relleno 1","mn":"ADBE Vector Graphic - Fill","hd":false},{"ty":"tr","p":{"a":0,"k":[45.358,46.529],"ix":2},"a":{"a":0,"k":[0,0],"ix":1},"s":{"a":0,"k":[100,100],"ix":3},"r":{"a":0,"k":0,"ix":6},"o":{"a":0,"k":100,"ix":7},"sk":{"a":0,"k":0,"ix":4},"sa":{"a":0,"k":0,"ix":5},"nm":"Transformar"}],"nm":"Grupo 7","np":2,"cix":2,"bm":0,"ix":7,"mn":"ADBE Vector Group","hd":false},{"ty":"gr","it":[{"ind":0,"ty":"sh","ix":1,"ks":{"a":0,"k":{"i":[[0,-25.198],[-25.198,0],[0,25.198],[25.198,0]],"o":[[0,25.198],[25.198,0],[0,-25.198],[-25.198,0]],"v":[[-45.764,-0.016],[-0.139,45.609],[45.486,-0.016],[-0.139,-45.641]],"c":true},"ix":2},"nm":"Trazado 1","mn":"ADBE Vector Shape - Group","hd":false},{"ty":"fl","c":{"a":0,"k":[0.169000004787,0.165000002992,0.176000004189,1],"ix":4},"o":{"a":0,"k":100,"ix":5},"r":1,"bm":0,"nm":"Relleno 1","mn":"ADBE Vector Graphic - Fill","hd":false},{"ty":"tr","p":{"a":0,"k":[45.486,45.609],"ix":2},"a":{"a":0,"k":[0,0],"ix":1},"s":{"a":0,"k":[100,100],"ix":3},"r":{"a":0,"k":0,"ix":6},"o":{"a":0,"k":100,"ix":7},"sk":{"a":0,"k":0,"ix":4},"sa":{"a":0,"k":0,"ix":5},"nm":"Transformar"}],"nm":"Grupo 8","np":4,"cix":2,"bm":0,"ix":8,"mn":"ADBE Vector Group","hd":false}],"ip":0,"op":420,"st":0,"bm":0},{"ddd":0,"ind":5,"ty":4,"nm":"rueda 1 contornos","sr":1,"ks":{"o":{"a":0,"k":100,"ix":11},"r":{"a":1,"k":[{"i":{"x":[0.833],"y":[0.833]},"o":{"x":[0.167],"y":[0.167]},"t":0,"s":[0]},{"i":{"x":[0.833],"y":[0.833]},"o":{"x":[0.167],"y":[0.167]},"t":163,"s":[-1470]},{"t":415,"s":[-2550]}],"ix":10},"p":{"a":1,"k":[{"i":{"x":0.833,"y":0.833},"o":{"x":0.167,"y":0.167},"t":0,"s":[880.5,252.99999999999997,0],"to":[-81.333,0,0],"ti":[81.333,0,0]},{"t":56,"s":[392.5,252.99999999999997,0]}],"ix":2},"a":{"a":0,"k":[46,46,0],"ix":1},"s":{"a":0,"k":[87,87,100],"ix":6}},"ao":0,"shapes":[{"ty":"gr","it":[{"ind":0,"ty":"sh","ix":1,"ks":{"a":0,"k":{"i":[[0,-2.305],[2.305,0],[0,2.305],[-2.305,0]],"o":[[0,2.305],[-2.305,0],[0,-2.305],[2.305,0]],"v":[[4.173,0.001],[0,4.174],[-4.173,0.001],[0,-4.174]],"c":true},"ix":2},"nm":"Trazado 1","mn":"ADBE Vector Shape - Group","hd":false},{"ty":"fl","c":{"a":0,"k":[0.243000000598,0.263000009574,0.277999997606,1],"ix":4},"o":{"a":0,"k":100,"ix":5},"r":1,"bm":0,"nm":"Relleno 1","mn":"ADBE Vector Graphic - Fill","hd":false},{"ty":"tr","p":{"a":0,"k":[45.625,46.528],"ix":2},"a":{"a":0,"k":[0,0],"ix":1},"s":{"a":0,"k":[100,100],"ix":3},"r":{"a":0,"k":0,"ix":6},"o":{"a":0,"k":100,"ix":7},"sk":{"a":0,"k":0,"ix":4},"sa":{"a":0,"k":0,"ix":5},"nm":"Transformar"}],"nm":"Grupo 1","np":2,"cix":2,"bm":0,"ix":1,"mn":"ADBE Vector Group","hd":false},{"ty":"gr","it":[{"ind":0,"ty":"sh","ix":1,"ks":{"a":0,"k":{"i":[[0.001,-4.901],[0.307,-3.339],[4.556,6.38],[-1.902,-0.183]],"o":[[0,2.182],[-7.776,-2.092],[3.365,-1.696],[2.165,0.209]],"v":[[9.685,-2.629],[9.326,9.51],[-9.686,-3.717],[4.355,-9.327]],"c":true},"ix":2},"nm":"Trazado 1","mn":"ADBE Vector Shape - Group","hd":false},{"ty":"fl","c":{"a":0,"k":[0.243000000598,0.263000009574,0.277999997606,1],"ix":4},"o":{"a":0,"k":100,"ix":5},"r":1,"bm":0,"nm":"Relleno 1","mn":"ADBE Vector Graphic - Fill","hd":false},{"ty":"tr","p":{"a":0,"k":[27.087,69.225],"ix":2},"a":{"a":0,"k":[0,0],"ix":1},"s":{"a":0,"k":[100,100],"ix":3},"r":{"a":0,"k":0,"ix":6},"o":{"a":0,"k":100,"ix":7},"sk":{"a":0,"k":0,"ix":4},"sa":{"a":0,"k":0,"ix":5},"nm":"Transformar"}],"nm":"Grupo 2","np":2,"cix":2,"bm":0,"ix":2,"mn":"ADBE Vector Group","hd":false},{"ty":"gr","it":[{"ind":0,"ty":"sh","ix":1,"ks":{"a":0,"k":{"i":[[-0.678,1.585],[-4.669,-1.49],[-2.784,-1.122],[7.199,-2.427]],"o":[[0.856,-1.999],[1.846,0.589],[-4.17,6.181],[-0.531,-3.846]],"v":[[-8.736,-4.735],[-0.95,-8.084],[9.413,-3.775],[-8.09,9.574]],"c":true},"ix":2},"nm":"Trazado 1","mn":"ADBE Vector Shape - Group","hd":false},{"ty":"fl","c":{"a":0,"k":[0.243000000598,0.263000009574,0.277999997606,1],"ix":4},"o":{"a":0,"k":100,"ix":5},"r":1,"bm":0,"nm":"Relleno 1","mn":"ADBE Vector Graphic - Fill","hd":false},{"ty":"tr","p":{"a":0,"k":[64.406,68.541],"ix":2},"a":{"a":0,"k":[0,0],"ix":1},"s":{"a":0,"k":[100,100],"ix":3},"r":{"a":0,"k":0,"ix":6},"o":{"a":0,"k":100,"ix":7},"sk":{"a":0,"k":0,"ix":4},"sa":{"a":0,"k":0,"ix":5},"nm":"Transformar"}],"nm":"Grupo 3","np":2,"cix":2,"bm":0,"ix":3,"mn":"ADBE Vector Group","hd":false},{"ty":"gr","it":[{"ind":0,"ty":"sh","ix":1,"ks":{"a":0,"k":{"i":[[-2.748,4.044],[-1.934,2.415],[-0.021,-7.812],[1.616,0.308]],"o":[[1.124,-1.655],[4.384,5.758],[-3.783,-0.62],[-3.932,-0.749]],"v":[[-6.087,-1.73],[1.814,-10.383],[8.835,10.383],[-2.972,8.46]],"c":true},"ix":2},"nm":"Trazado 1","mn":"ADBE Vector Shape - Group","hd":false},{"ty":"fl","c":{"a":0,"k":[0.243000000598,0.263000009574,0.277999997606,1],"ix":4},"o":{"a":0,"k":100,"ix":5},"r":1,"bm":0,"nm":"Relleno 1","mn":"ADBE Vector Graphic - Fill","hd":false},{"ty":"tr","p":{"a":0,"k":[70.832,35.113],"ix":2},"a":{"a":0,"k":[0,0],"ix":1},"s":{"a":0,"k":[100,100],"ix":3},"r":{"a":0,"k":0,"ix":6},"o":{"a":0,"k":100,"ix":7},"sk":{"a":0,"k":0,"ix":4},"sa":{"a":0,"k":0,"ix":5},"nm":"Transformar"}],"nm":"Grupo 4","np":2,"cix":2,"bm":0,"ix":4,"mn":"ADBE Vector Group","hd":false},{"ty":"gr","it":[{"ind":0,"ty":"sh","ix":1,"ks":{"a":0,"k":{"i":[[1.373,-0.97],[3.196,3.715],[2.048,2.982],[-4.156,0],[-3.504,-1.207]],"o":[[-1.776,1.254],[-1.561,-1.813],[3.686,-1.352],[3.914,0],[-1.575,3.539]],"v":[[4.979,5.132],[-4.788,4.872],[-11.499,-6.495],[0.326,-8.587],[11.499,-6.717]],"c":true},"ix":2},"nm":"Trazado 1","mn":"ADBE Vector Shape - Group","hd":false},{"ty":"fl","c":{"a":0,"k":[0.243000000598,0.263000009574,0.277999997606,1],"ix":4},"o":{"a":0,"k":100,"ix":5},"r":1,"bm":0,"nm":"Relleno 1","mn":"ADBE Vector Graphic - Fill","hd":false},{"ty":"tr","p":{"a":0,"k":[45.021,19.857],"ix":2},"a":{"a":0,"k":[0,0],"ix":1},"s":{"a":0,"k":[100,100],"ix":3},"r":{"a":0,"k":0,"ix":6},"o":{"a":0,"k":100,"ix":7},"sk":{"a":0,"k":0,"ix":4},"sa":{"a":0,"k":0,"ix":5},"nm":"Transformar"}],"nm":"Grupo 5","np":2,"cix":2,"bm":0,"ix":5,"mn":"ADBE Vector Group","hd":false},{"ty":"gr","it":[{"ind":0,"ty":"sh","ix":1,"ks":{"a":0,"k":{"i":[[4.672,-1.479],[3.108,-0.708],[0,0.284],[-4.314,5.738],[-0.375,-1.749]],"o":[[-1.966,0.623],[-0.007,-0.282],[0,-7.732],[2.666,2.807],[0.456,2.127]],"v":[[3.896,7.859],[-8.548,10.725],[-8.568,9.878],[-1.697,-10.725],[7.495,0.001]],"c":true},"ix":2},"nm":"Trazado 1","mn":"ADBE Vector Shape - Group","hd":false},{"ty":"fl","c":{"a":0,"k":[0.243000000598,0.263000009574,0.277999997606,1],"ix":4},"o":{"a":0,"k":100,"ix":5},"r":1,"bm":0,"nm":"Relleno 1","mn":"ADBE Vector Graphic - Fill","hd":false},{"ty":"tr","p":{"a":0,"k":[19.592,35.715],"ix":2},"a":{"a":0,"k":[0,0],"ix":1},"s":{"a":0,"k":[100,100],"ix":3},"r":{"a":0,"k":0,"ix":6},"o":{"a":0,"k":100,"ix":7},"sk":{"a":0,"k":0,"ix":4},"sa":{"a":0,"k":0,"ix":5},"nm":"Transformar"}],"nm":"Grupo 6","np":2,"cix":2,"bm":0,"ix":6,"mn":"ADBE Vector Group","hd":false},{"ty":"gr","it":[{"ind":0,"ty":"sh","ix":1,"ks":{"a":0,"k":{"i":[[-1.966,0.623],[0.456,2.127],[2.666,2.807],[-6.271,2.302],[-1.561,-1.813],[-1.777,1.255],[-1.575,3.539],[-4.063,-5.298],[1.133,-1.654],[-1.669,-1.394],[-3.812,-0.62],[0,-0.032],[3.693,-5.474],[1.847,0.589],[0.856,-2],[-0.531,-3.846],[3.838,0],[2.85,0.767],[0,2.183],[2.164,0.208],[3.364,-1.696],[0.173,7.103]],"o":[[4.672,-1.479],[-0.375,-1.749],[3.944,-5.247],[2.047,2.981],[3.196,3.715],[1.373,-0.969],[6.439,2.217],[-1.949,2.415],[-2.768,4.044],[1.268,1.059],[0,0.032],[0,7.101],[-2.784,-1.122],[-4.669,-1.489],[-0.678,1.585],[-3.446,1.162],[-3.091,0],[0.307,-3.339],[0.001,-4.9],[-1.902,-0.183],[-3.857,-5.402],[3.108,-0.708]],"v":[[-26.074,-2.374],[-20.453,-12.259],[-27.462,-21.539],[-11.835,-33.167],[-5.621,-25.251],[5.677,-23.966],[11.164,-33.388],[27.237,-21.799],[22.323,-15.13],[23.987,-3.881],[34.31,-1.032],[34.313,-0.936],[28.462,18.237],[20.952,15.564],[10.655,20.39],[10.959,31.586],[-0.011,33.388],[-8.945,32.206],[-8.586,23.111],[-16.31,14.767],[-27.956,18.98],[-34.313,-0.088]],"c":true},"ix":2},"nm":"Trazado 1","mn":"ADBE Vector Shape - Group","hd":false},{"ty":"fl","c":{"a":0,"k":[0.666999966491,0.666999966491,0.666999966491,1],"ix":4},"o":{"a":0,"k":100,"ix":5},"r":1,"bm":0,"nm":"Relleno 1","mn":"ADBE Vector Graphic - Fill","hd":false},{"ty":"tr","p":{"a":0,"k":[45.358,46.529],"ix":2},"a":{"a":0,"k":[0,0],"ix":1},"s":{"a":0,"k":[100,100],"ix":3},"r":{"a":0,"k":0,"ix":6},"o":{"a":0,"k":100,"ix":7},"sk":{"a":0,"k":0,"ix":4},"sa":{"a":0,"k":0,"ix":5},"nm":"Transformar"}],"nm":"Grupo 7","np":2,"cix":2,"bm":0,"ix":7,"mn":"ADBE Vector Group","hd":false},{"ty":"gr","it":[{"ind":0,"ty":"sh","ix":1,"ks":{"a":0,"k":{"i":[[0,-25.198],[-25.198,0],[0,25.198],[25.198,0]],"o":[[0,25.198],[25.198,0],[0,-25.198],[-25.198,0]],"v":[[-45.764,-0.016],[-0.139,45.609],[45.486,-0.016],[-0.139,-45.641]],"c":true},"ix":2},"nm":"Trazado 1","mn":"ADBE Vector Shape - Group","hd":false},{"ty":"fl","c":{"a":0,"k":[0.169000004787,0.165000002992,0.176000004189,1],"ix":4},"o":{"a":0,"k":100,"ix":5},"r":1,"bm":0,"nm":"Relleno 1","mn":"ADBE Vector Graphic - Fill","hd":false},{"ty":"tr","p":{"a":0,"k":[45.486,45.609],"ix":2},"a":{"a":0,"k":[0,0],"ix":1},"s":{"a":0,"k":[100,100],"ix":3},"r":{"a":0,"k":0,"ix":6},"o":{"a":0,"k":100,"ix":7},"sk":{"a":0,"k":0,"ix":4},"sa":{"a":0,"k":0,"ix":5},"nm":"Transformar"}],"nm":"Grupo 8","np":4,"cix":2,"bm":0,"ix":8,"mn":"ADBE Vector Group","hd":false}],"ip":0,"op":420,"st":0,"bm":0},{"ddd":0,"ind":7,"ty":4,"nm":"carro contornos","sr":1,"ks":{"o":{"a":0,"k":100,"ix":11},"r":{"a":0,"k":0,"ix":10},"p":{"a":1,"k":[{"i":{"x":0.833,"y":0.833},"o":{"x":0.167,"y":0.167},"t":0,"s":[721.5,204.99999999999997,0],"to":[-78.667,0,0],"ti":[78.667,0,0]},{"t":56,"s":[249.5,204.99999999999997,0]}],"ix":2},"a":{"a":0,"k":[282,256,0],"ix":1},"s":{"a":0,"k":[87,87,100],"ix":6}},"ao":0,"shapes":[{"ty":"gr","it":[{"ind":0,"ty":"sh","ix":1,"ks":{"a":0,"k":{"i":[[0,0],[0,0],[0,0],[3.592,0.351]],"o":[[0,0],[0,0],[-3.215,-0.556],[0,0]],"v":[[-16.646,19.151],[-5.62,18.375],[16.647,-17.986],[6.848,-19.151]],"c":true},"ix":2},"nm":"Trazado 1","mn":"ADBE Vector Shape - Group","hd":false},{"ty":"fl","c":{"a":0,"k":[0.352999997606,0.372999991623,0.388000009574,1],"ix":4},"o":{"a":0,"k":100,"ix":5},"r":1,"bm":0,"nm":"Relleno 1","mn":"ADBE Vector Graphic - Fill","hd":false},{"ty":"tr","p":{"a":0,"k":[384.026,191.217],"ix":2},"a":{"a":0,"k":[0,0],"ix":1},"s":{"a":0,"k":[100,100],"ix":3},"r":{"a":0,"k":0,"ix":6},"o":{"a":0,"k":100,"ix":7},"sk":{"a":0,"k":0,"ix":4},"sa":{"a":0,"k":0,"ix":5},"nm":"Transformar"}],"nm":"Grupo 1","np":2,"cix":2,"bm":0,"ix":1,"mn":"ADBE Vector Group","hd":false},{"ty":"gr","it":[{"ind":0,"ty":"sh","ix":1,"ks":{"a":0,"k":{"i":[[0,0],[0,0],[0,0],[7.158,0.183]],"o":[[0,0],[0,0],[-5.933,-0.443],[0,0]],"v":[[-22.515,20.645],[-1.617,19.709],[22.515,-19.57],[2.89,-20.645]],"c":true},"ix":2},"nm":"Trazado 1","mn":"ADBE Vector Shape - Group","hd":false},{"ty":"fl","c":{"a":0,"k":[0.352999997606,0.372999991623,0.388000009574,1],"ix":4},"o":{"a":0,"k":100,"ix":5},"r":1,"bm":0,"nm":"Relleno 1","mn":"ADBE Vector Graphic - Fill","hd":false},{"ty":"tr","p":{"a":0,"k":[361.569,191.114],"ix":2},"a":{"a":0,"k":[0,0],"ix":1},"s":{"a":0,"k":[100,100],"ix":3},"r":{"a":0,"k":0,"ix":6},"o":{"a":0,"k":100,"ix":7},"sk":{"a":0,"k":0,"ix":4},"sa":{"a":0,"k":0,"ix":5},"nm":"Transformar"}],"nm":"Grupo 2","np":2,"cix":2,"bm":0,"ix":2,"mn":"ADBE Vector Group","hd":false},{"ty":"gr","it":[{"ind":0,"ty":"sh","ix":1,"ks":{"a":0,"k":{"i":[[0,0],[0,0],[0,0],[4.623,-0.816]],"o":[[0,0],[0,0],[-4.573,0.397],[0,0]],"v":[[-20.947,23.785],[-7.149,22.38],[20.947,-23.785],[7.022,-21.697]],"c":true},"ix":2},"nm":"Trazado 1","mn":"ADBE Vector Shape - Group","hd":false},{"ty":"fl","c":{"a":0,"k":[0.352999997606,0.372999991623,0.388000009574,1],"ix":4},"o":{"a":0,"k":100,"ix":5},"r":1,"bm":0,"nm":"Relleno 1","mn":"ADBE Vector Graphic - Fill","hd":false},{"ty":"tr","p":{"a":0,"k":[277.622,194.509],"ix":2},"a":{"a":0,"k":[0,0],"ix":1},"s":{"a":0,"k":[100,100],"ix":3},"r":{"a":0,"k":0,"ix":6},"o":{"a":0,"k":100,"ix":7},"sk":{"a":0,"k":0,"ix":4},"sa":{"a":0,"k":0,"ix":5},"nm":"Transformar"}],"nm":"Grupo 3","np":2,"cix":2,"bm":0,"ix":3,"mn":"ADBE Vector Group","hd":false},{"ty":"gr","it":[{"ind":0,"ty":"sh","ix":1,"ks":{"a":0,"k":{"i":[[0,0],[-4.918,0.353],[0,0],[10,-4.784]],"o":[[4.004,-0.287],[0,0],[-11.456,2.944],[0,0]],"v":[[-28.132,23.281],[-1.367,21.362],[28.132,-23.281],[-7.919,-12.56]],"c":true},"ix":2},"nm":"Trazado 1","mn":"ADBE Vector Shape - Group","hd":false},{"ty":"fl","c":{"a":0,"k":[0.352999997606,0.372999991623,0.388000009574,1],"ix":4},"o":{"a":0,"k":100,"ix":5},"r":1,"bm":0,"nm":"Relleno 1","mn":"ADBE Vector Graphic - Fill","hd":false},{"ty":"tr","p":{"a":0,"k":[247.783,197.901],"ix":2},"a":{"a":0,"k":[0,0],"ix":1},"s":{"a":0,"k":[100,100],"ix":3},"r":{"a":0,"k":0,"ix":6},"o":{"a":0,"k":100,"ix":7},"sk":{"a":0,"k":0,"ix":4},"sa":{"a":0,"k":0,"ix":5},"nm":"Transformar"}],"nm":"Grupo 4","np":2,"cix":2,"bm":0,"ix":4,"mn":"ADBE Vector Group","hd":false},{"ty":"gr","it":[{"ind":0,"ty":"sh","ix":1,"ks":{"a":0,"k":{"i":[[0,0],[-4.884,0.921]],"o":[[0,0],[0,0]],"v":[[-4.883,-1.106],[4.883,0.184]],"c":false},"ix":2},"nm":"Trazado 1","mn":"ADBE Vector Shape - Group","hd":false},{"ty":"fl","c":{"a":0,"k":[0.00784313725490196,0.6470588235294118,0.6470588235294118,1],"ix":4},"o":{"a":0,"k":100,"ix":5},"r":1,"bm":0,"nm":"Relleno 1","mn":"ADBE Vector Graphic - Fill","hd":false},{"ty":"tr","p":{"a":0,"k":[208.24,222.288],"ix":2},"a":{"a":0,"k":[0,0],"ix":1},"s":{"a":0,"k":[100,100],"ix":3},"r":{"a":0,"k":0,"ix":6},"o":{"a":0,"k":100,"ix":7},"sk":{"a":0,"k":0,"ix":4},"sa":{"a":0,"k":0,"ix":5},"nm":"Transformar"}],"nm":"Grupo 5","np":2,"cix":2,"bm":0,"ix":5,"mn":"ADBE Vector Group","hd":false},{"ty":"gr","it":[{"ind":0,"ty":"sh","ix":1,"ks":{"a":0,"k":{"i":[[0,0],[3.599,-1.8],[-8.278,-2.34],[-3.239,-1.44],[-0.72,1.979],[0.359,2.844]],"o":[[-1.98,-1.62],[-3.599,1.799],[8.278,2.339],[3.239,1.44],[0.72,-1.98],[-0.36,-2.844]],"v":[[27.265,-7.918],[-22.765,-7.918],[-22.765,-2.519],[8.189,5.399],[28.884,7.739],[30.684,-0.395]],"c":true},"ix":2},"nm":"Trazado 1","mn":"ADBE Vector Shape - Group","hd":false},{"ty":"fl","c":{"a":0,"k":[1,0.663000009574,0.063000002094,1],"ix":4},"o":{"a":0,"k":100,"ix":5},"r":1,"bm":0,"nm":"Relleno 1","mn":"ADBE Vector Graphic - Fill","hd":false},{"ty":"tr","p":{"a":0,"k":[503.328,223.068],"ix":2},"a":{"a":0,"k":[0,0],"ix":1},"s":{"a":0,"k":[100,100],"ix":3},"r":{"a":0,"k":0,"ix":6},"o":{"a":0,"k":100,"ix":7},"sk":{"a":0,"k":0,"ix":4},"sa":{"a":0,"k":0,"ix":5},"nm":"Transformar"}],"nm":"Grupo 6","np":2,"cix":2,"bm":0,"ix":6,"mn":"ADBE Vector Group","hd":false},{"ty":"gr","it":[{"ind":0,"ty":"sh","ix":1,"ks":{"a":0,"k":{"i":[[0.745,3.087],[27.397,-22.305],[-6.303,1.455],[-5.334,3.879]],"o":[[-6.546,-0.97],[1.94,1.697],[6.304,-1.455],[5.334,-3.879]],"v":[[30.54,-12.244],[-31.285,11.516],[-19.163,11.516],[-3.403,7.153]],"c":true},"ix":2},"nm":"Trazado 1","mn":"ADBE Vector Shape - Group","hd":false},{"ty":"fl","c":{"a":0,"k":[0.987999949736,0.944999964097,0.395999983245,1],"ix":4},"o":{"a":0,"k":100,"ix":5},"r":1,"bm":0,"nm":"Relleno 1","mn":"ADBE Vector Graphic - Fill","hd":false},{"ty":"tr","p":{"a":0,"k":[79.602,236.374],"ix":2},"a":{"a":0,"k":[0,0],"ix":1},"s":{"a":0,"k":[100,100],"ix":3},"r":{"a":0,"k":0,"ix":6},"o":{"a":0,"k":100,"ix":7},"sk":{"a":0,"k":0,"ix":4},"sa":{"a":0,"k":0,"ix":5},"nm":"Transformar"}],"nm":"Grupo 7","np":2,"cix":2,"bm":0,"ix":7,"mn":"ADBE Vector Group","hd":false},{"ty":"gr","it":[{"ind":0,"ty":"sh","ix":1,"ks":{"a":0,"k":{"i":[[0,0],[0.97,-2.91],[-2.909,-5.576],[0,6.789]],"o":[[-4.364,-1.697],[-0.97,2.909],[2.91,5.578],[0,0]],"v":[[7.88,-16.972],[-4.971,-11.88],[-4.971,13.091],[7.88,7.515]],"c":true},"ix":2},"nm":"Trazado 1","mn":"ADBE Vector Shape - Group","hd":false},{"ty":"fl","c":{"a":0,"k":[1,0.972999961703,0.630999995213,1],"ix":4},"o":{"a":0,"k":100,"ix":5},"r":1,"bm":0,"nm":"Relleno 1","mn":"ADBE Vector Graphic - Fill","hd":false},{"ty":"tr","p":{"a":0,"k":[45.286,286.199],"ix":2},"a":{"a":0,"k":[0,0],"ix":1},"s":{"a":0,"k":[100,100],"ix":3},"r":{"a":0,"k":0,"ix":6},"o":{"a":0,"k":100,"ix":7},"sk":{"a":0,"k":0,"ix":4},"sa":{"a":0,"k":0,"ix":5},"nm":"Transformar"}],"nm":"Grupo 8","np":2,"cix":2,"bm":0,"ix":8,"mn":"ADBE Vector Group","hd":false},{"ty":"gr","it":[{"ind":0,"ty":"sh","ix":1,"ks":{"a":0,"k":{"i":[[0,0],[-2.164,-0.866],[-2.387,2.686],[4.478,4.179]],"o":[[-0.896,5.97],[4.478,1.791],[2.388,-2.687],[-4.477,-4.178]],"v":[[-17.126,-16.715],[-17.126,14.925],[9.738,12.239],[14.812,-11.641]],"c":true},"ix":2},"nm":"Trazado 1","mn":"ADBE Vector Shape - Group","hd":false},{"ty":"fl","c":{"a":0,"k":[0.184000007779,0.2,0.20800000359,1],"ix":4},"o":{"a":0,"k":100,"ix":5},"r":1,"bm":0,"nm":"Relleno 1","mn":"ADBE Vector Graphic - Fill","hd":false},{"ty":"tr","p":{"a":0,"k":[426.495,191.455],"ix":2},"a":{"a":0,"k":[0,0],"ix":1},"s":{"a":0,"k":[100,100],"ix":3},"r":{"a":0,"k":0,"ix":6},"o":{"a":0,"k":100,"ix":7},"sk":{"a":0,"k":0,"ix":4},"sa":{"a":0,"k":0,"ix":5},"nm":"Transformar"}],"nm":"Grupo 9","np":2,"cix":2,"bm":0,"ix":9,"mn":"ADBE Vector Group","hd":false},{"ty":"gr","it":[{"ind":0,"ty":"sh","ix":1,"ks":{"a":0,"k":{"i":[[0,0],[3.582,-2.686],[-2.389,-1.791],[-1.791,2.388]],"o":[[-7.164,-3.283],[-0.598,11.343],[2.387,1.791],[0.597,-5.373]],"v":[[39.849,-16.865],[-38.057,-19.552],[-38.057,20.447],[39.849,15.372]],"c":true},"ix":2},"nm":"Trazado 1","mn":"ADBE Vector Shape - Group","hd":false},{"ty":"fl","c":{"a":0,"k":[0.184000007779,0.2,0.20800000359,1],"ix":4},"o":{"a":0,"k":100,"ix":5},"r":1,"bm":0,"nm":"Relleno 1","mn":"ADBE Vector Graphic - Fill","hd":false},{"ty":"tr","p":{"a":0,"k":[364.446,191.008],"ix":2},"a":{"a":0,"k":[0,0],"ix":1},"s":{"a":0,"k":[100,100],"ix":3},"r":{"a":0,"k":0,"ix":6},"o":{"a":0,"k":100,"ix":7},"sk":{"a":0,"k":0,"ix":4},"sa":{"a":0,"k":0,"ix":5},"nm":"Transformar"}],"nm":"Grupo 10","np":2,"cix":2,"bm":0,"ix":10,"mn":"ADBE Vector Group","hd":false},{"ty":"gr","it":[{"ind":0,"ty":"sh","ix":1,"ks":{"a":0,"k":{"i":[[0.886,4.15],[18.675,-14.525],[7.707,-5.775],[-9.803,0.742],[-2.668,1.779]],"o":[[-40.904,2.075],[11.858,-0.297],[-1.888,1.789],[18.083,-1.186],[2.668,-1.778]],"v":[[52.32,-26.013],[-53.206,6.892],[-43.424,23.941],[-32.456,25.271],[41.948,16.97]],"c":true},"ix":2},"nm":"Trazado 1","mn":"ADBE Vector Shape - Group","hd":false},{"ty":"fl","c":{"a":0,"k":[0.184000007779,0.2,0.20800000359,1],"ix":4},"o":{"a":0,"k":100,"ix":5},"r":1,"bm":0,"nm":"Relleno 1","mn":"ADBE Vector Graphic - Fill","hd":false},{"ty":"tr","p":{"a":0,"k":[260.112,195.529],"ix":2},"a":{"a":0,"k":[0,0],"ix":1},"s":{"a":0,"k":[100,100],"ix":3},"r":{"a":0,"k":0,"ix":6},"o":{"a":0,"k":100,"ix":7},"sk":{"a":0,"k":0,"ix":4},"sa":{"a":0,"k":0,"ix":5},"nm":"Transformar"}],"nm":"Grupo 11","np":2,"cix":2,"bm":0,"ix":11,"mn":"ADBE Vector Group","hd":false},{"ty":"gr","it":[{"ind":0,"ty":"sh","ix":1,"ks":{"a":0,"k":{"i":[[8.918,-1.318],[3.853,-2.371],[10.672,-1.625],[16.007,-8.299],[1.779,-5.929],[1.482,-3.261],[0.592,-3.261],[0.296,-1.187],[-0.689,-1.513],[-1.186,-0.89],[-1.482,-0.592],[-4.15,-0.296],[-6.522,0.593],[-0.89,-56.322],[-6.817,0.593],[-13.636,0],[-17.785,0.89],[-0.593,-41.203],[-3.557,2.371],[0.296,3.853],[0.593,2.371],[0.297,3.854],[0,1.483],[0.593,1.186],[0.297,2.668],[0.296,2.371],[4.743,3.557],[1.482,2.668],[-0.89,2.372],[-0.592,3.26],[6.844,2.843]],"o":[[-78.212,11.561],[-11.858,3.26],[-10.671,1.625],[-16.007,8.301],[-1.778,5.928],[-1.482,3.261],[-0.593,3.261],[-0.297,1.185],[0.688,1.514],[1.185,0.888],[1.482,0.593],[-4.446,-62.547],[6.521,-0.593],[33.496,-1.778],[6.819,-0.594],[0,-52.468],[17.786,-0.888],[13.932,-3.853],[3.558,-2.372],[-0.297,-3.854],[-0.593,-2.371],[-0.296,-3.853],[0,-1.482],[-0.593,-1.186],[-0.296,-2.667],[-0.297,-2.372],[-4.742,-3.557],[-1.482,-2.668],[0.888,-2.372],[-5.039,0.296],[-46.973,-19.513]],"v":[[9.879,-79.617],[-111.361,-28.038],[-163.237,-18.102],[-213.333,-8.178],[-246.831,14.648],[-249.794,31.544],[-254.833,41.919],[-253.352,71.563],[-254.93,77.756],[-244.458,81.938],[-243.569,85.198],[-213.926,88.755],[-164.422,26.208],[-112.843,85.791],[58.195,84.013],[107.996,84.309],[157.797,23.54],[209.673,75.712],[243.168,68.302],[255.323,56.148],[253.841,36.287],[249.097,31.248],[248.207,10.794],[250.579,5.755],[246.43,-6.992],[247.911,-15.588],[238.425,-29.52],[213.526,-49.678],[212.934,-58.867],[221.233,-66.87],[191.887,-69.242]],"c":true},"ix":2},"nm":"Trazado 1","mn":"ADBE Vector Shape - Group","hd":false},{"ty":"fl","c":{"a":0,"k":[0.00784313725490196,0.6470588235294118,0.6470588235294118,1],"ix":4},"o":{"a":0,"k":100,"ix":5},"r":1,"bm":0,"nm":"Relleno 1","mn":"ADBE Vector Graphic - Fill","hd":false},{"ty":"tr","p":{"a":0,"k":[288.032,237.573],"ix":2},"a":{"a":0,"k":[0,0],"ix":1},"s":{"a":0,"k":[100,100],"ix":3},"r":{"a":0,"k":0,"ix":6},"o":{"a":0,"k":100,"ix":7},"sk":{"a":0,"k":0,"ix":4},"sa":{"a":0,"k":0,"ix":5},"nm":"Transformar"}],"nm":"Grupo 12","np":2,"cix":2,"bm":0,"ix":12,"mn":"ADBE Vector Group","hd":false},{"ty":"gr","it":[{"ind":0,"ty":"sh","ix":1,"ks":{"a":0,"k":{"i":[[0,0],[0,0],[0,0],[4.416,0.432]],"o":[[0,0],[0,0],[-3.68,-0.576],[0,0]],"v":[[-20.04,22.792],[-6.376,21.704],[20.04,-21.256],[7.992,-22.792]],"c":true},"ix":2},"nm":"Trazado 1","mn":"ADBE Vector Shape - Group","hd":false},{"ty":"fl","c":{"a":0,"k":[0.352999997606,0.372999991623,0.388000009574,1],"ix":4},"o":{"a":0,"k":100,"ix":5},"r":1,"bm":0,"nm":"Relleno 1","mn":"ADBE Vector Graphic - Fill","hd":false},{"ty":"tr","p":{"a":0,"k":[394.851,191.012],"ix":2},"a":{"a":0,"k":[0,0],"ix":1},"s":{"a":0,"k":[100,100],"ix":3},"r":{"a":0,"k":0,"ix":6},"o":{"a":0,"k":100,"ix":7},"sk":{"a":0,"k":0,"ix":4},"sa":{"a":0,"k":0,"ix":5},"nm":"Transformar"}],"nm":"Grupo 13","np":2,"cix":2,"bm":0,"ix":13,"mn":"ADBE Vector Group","hd":false},{"ty":"gr","it":[{"ind":0,"ty":"sh","ix":1,"ks":{"a":0,"k":{"i":[[0,0],[0,0],[0,0],[8.8,0.224]],"o":[[0,0],[0,0],[-7.296,-0.544],[0,0]],"v":[[-27.552,25.144],[-1.361,23.048],[27.552,-23.976],[3.36,-25.144]],"c":true},"ix":2},"nm":"Trazado 1","mn":"ADBE Vector Shape - Group","hd":false},{"ty":"fl","c":{"a":0,"k":[0.352999997606,0.372999991623,0.388000009574,1],"ix":4},"o":{"a":0,"k":100,"ix":5},"r":1,"bm":0,"nm":"Relleno 1","mn":"ADBE Vector Graphic - Fill","hd":false},{"ty":"tr","p":{"a":0,"k":[366.956,191.492],"ix":2},"a":{"a":0,"k":[0,0],"ix":1},"s":{"a":0,"k":[100,100],"ix":3},"r":{"a":0,"k":0,"ix":6},"o":{"a":0,"k":100,"ix":7},"sk":{"a":0,"k":0,"ix":4},"sa":{"a":0,"k":0,"ix":5},"nm":"Transformar"}],"nm":"Grupo 14","np":2,"cix":2,"bm":0,"ix":14,"mn":"ADBE Vector Group","hd":false},{"ty":"gr","it":[{"ind":0,"ty":"sh","ix":1,"ks":{"a":0,"k":{"i":[[0,0],[0,0],[0,0],[4.624,-0.816]],"o":[[0,0],[0,0],[-4.688,0.256],[0,0]],"v":[[-23.848,28.216],[-10.184,27.128],[23.848,-28.216],[9.88,-26.632]],"c":true},"ix":2},"nm":"Trazado 1","mn":"ADBE Vector Shape - Group","hd":false},{"ty":"fl","c":{"a":0,"k":[0.352999997606,0.372999991623,0.388000009574,1],"ix":4},"o":{"a":0,"k":100,"ix":5},"r":1,"bm":0,"nm":"Relleno 1","mn":"ADBE Vector Graphic - Fill","hd":false},{"ty":"tr","p":{"a":0,"k":[270.147,195.844],"ix":2},"a":{"a":0,"k":[0,0],"ix":1},"s":{"a":0,"k":[100,100],"ix":3},"r":{"a":0,"k":0,"ix":6},"o":{"a":0,"k":100,"ix":7},"sk":{"a":0,"k":0,"ix":4},"sa":{"a":0,"k":0,"ix":5},"nm":"Transformar"}],"nm":"Grupo 15","np":2,"cix":2,"bm":0,"ix":15,"mn":"ADBE Vector Group","hd":false},{"ty":"gr","it":[{"ind":0,"ty":"sh","ix":1,"ks":{"a":0,"k":{"i":[[0,0],[0,0],[0,0],[10,-4.784]],"o":[[0,0],[0,0],[-11.456,2.944],[0,0]],"v":[[-29.568,27.832],[-3.376,25.736],[29.568,-27.832],[-2.752,-15.768]],"c":true},"ix":2},"nm":"Trazado 1","mn":"ADBE Vector Shape - Group","hd":false},{"ty":"fl","c":{"a":0,"k":[0.352999997606,0.372999991623,0.388000009574,1],"ix":4},"o":{"a":0,"k":100,"ix":5},"r":1,"bm":0,"nm":"Relleno 1","mn":"ADBE Vector Graphic - Fill","hd":false},{"ty":"tr","p":{"a":0,"k":[240.443,199.06],"ix":2},"a":{"a":0,"k":[0,0],"ix":1},"s":{"a":0,"k":[100,100],"ix":3},"r":{"a":0,"k":0,"ix":6},"o":{"a":0,"k":100,"ix":7},"sk":{"a":0,"k":0,"ix":4},"sa":{"a":0,"k":0,"ix":5},"nm":"Transformar"}],"nm":"Grupo 16","np":2,"cix":2,"bm":0,"ix":16,"mn":"ADBE Vector Group","hd":false},{"ty":"gr","it":[{"ind":0,"ty":"sh","ix":1,"ks":{"a":0,"k":{"i":[[0,0],[0,0],[1.2,4.08],[2.816,-2.816],[-3.744,-3.744],[-7.12,1.04]],"o":[[0,0],[0,-4.336],[-6.912,-0.864],[-3.744,3.744],[3.136,3.136],[0,0]],"v":[[11.896,10.4],[11.896,0.352],[9.896,-12.272],[-8.488,-10.752],[-8.488,10.432],[12.232,11.648]],"c":true},"ix":2},"nm":"Trazado 1","mn":"ADBE Vector Shape - Group","hd":false},{"ty":"fl","c":{"a":0,"k":[1,0.368999974868,0.243000000598,1],"ix":4},"o":{"a":0,"k":100,"ix":5},"r":1,"bm":0,"nm":"Relleno 1","mn":"ADBE Vector Graphic - Fill","hd":false},{"ty":"tr","p":{"a":0,"k":[519.603,237.036],"ix":2},"a":{"a":0,"k":[0,0],"ix":1},"s":{"a":0,"k":[100,100],"ix":3},"r":{"a":0,"k":0,"ix":6},"o":{"a":0,"k":100,"ix":7},"sk":{"a":0,"k":0,"ix":4},"sa":{"a":0,"k":0,"ix":5},"nm":"Transformar"}],"nm":"Grupo 17","np":2,"cix":2,"bm":0,"ix":17,"mn":"ADBE Vector Group","hd":false},{"ty":"gr","it":[{"ind":0,"ty":"sh","ix":1,"ks":{"a":0,"k":{"i":[[0,0],[-19.072,2.681],[18.769,-16.264],[9.948,-2.365]],"o":[[0,0],[4.641,-0.65],[-5.872,5.085],[-8.068,1.901]],"v":[[-23.467,9.648],[8.023,-16.217],[8.885,2.487],[-19.587,14.966]],"c":true},"ix":2},"nm":"Trazado 1","mn":"ADBE Vector Shape - Group","hd":false},{"ty":"fl","c":{"a":0,"k":[1,0.952999997606,0.051000000449,1],"ix":4},"o":{"a":0,"k":100,"ix":5},"r":1,"bm":0,"nm":"Relleno 1","mn":"ADBE Vector Graphic - Fill","hd":false},{"ty":"tr","p":{"a":0,"k":[76.952,256.337],"ix":2},"a":{"a":0,"k":[0,0],"ix":1},"s":{"a":0,"k":[100,100],"ix":3},"r":{"a":0,"k":0,"ix":6},"o":{"a":0,"k":100,"ix":7},"sk":{"a":0,"k":0,"ix":4},"sa":{"a":0,"k":0,"ix":5},"nm":"Transformar"}],"nm":"Grupo 18","np":2,"cix":2,"bm":0,"ix":18,"mn":"ADBE Vector Group","hd":false},{"ty":"gr","it":[{"ind":0,"ty":"sh","ix":1,"ks":{"a":0,"k":{"i":[[10.128,6.176],[41.248,0],[4.416,-0.064],[0,0],[0,0],[-0.239,2],[0,0],[0,0]],"o":[[-12.368,-5.408],[-4.832,0],[0,0],[0,0],[0.401,-2.304],[0,0],[0,0],[1.296,-7.552]],"v":[[38.656,-17.184],[-44.416,-25.568],[-58.353,-25.456],[-62.832,25.568],[60.511,15.728],[61.487,9.232],[61.504,9.072],[61.536,8.912]],"c":true},"ix":2},"nm":"Trazado 1","mn":"ADBE Vector Shape - Group","hd":false},{"ty":"fl","c":{"a":0,"k":[0.243000000598,0.263000009574,0.277999997606,1],"ix":4},"o":{"a":0,"k":100,"ix":5},"r":1,"bm":0,"nm":"Relleno 1","mn":"ADBE Vector Graphic - Fill","hd":false},{"ty":"tr","p":{"a":0,"k":[395.116,191.628],"ix":2},"a":{"a":0,"k":[0,0],"ix":1},"s":{"a":0,"k":[100,100],"ix":3},"r":{"a":0,"k":0,"ix":6},"o":{"a":0,"k":100,"ix":7},"sk":{"a":0,"k":0,"ix":4},"sa":{"a":0,"k":0,"ix":5},"nm":"Transformar"}],"nm":"Grupo 19","np":2,"cix":2,"bm":0,"ix":19,"mn":"ADBE Vector Group","hd":false},{"ty":"gr","it":[{"ind":0,"ty":"sh","ix":1,"ks":{"a":0,"k":{"i":[[0,0],[0.112,-0.016],[0,0],[0,0],[0.896,0],[19.728,-13.824],[4.064,-9.92],[0,0]],"o":[[-8.944,0.304],[0,0],[0,0],[-0.896,-0.032],[-39.056,0],[-8.912,6.24],[0,0],[0,0]],"v":[[67.864,-31.288],[53.144,-30.664],[52.824,-30.648],[52.504,-30.648],[49.816,-30.68],[-47.88,6.344],[-67.864,31.288],[56.6,21.352]],"c":true},"ix":2},"nm":"Trazado 1","mn":"ADBE Vector Shape - Group","hd":false},{"ty":"fl","c":{"a":0,"k":[0.243000000598,0.263000009574,0.277999997606,1],"ix":4},"o":{"a":0,"k":100,"ix":5},"r":1,"bm":0,"nm":"Relleno 1","mn":"ADBE Vector Graphic - Fill","hd":false},{"ty":"tr","p":{"a":0,"k":[249.635,197.94],"ix":2},"a":{"a":0,"k":[0,0],"ix":1},"s":{"a":0,"k":[100,100],"ix":3},"r":{"a":0,"k":0,"ix":6},"o":{"a":0,"k":100,"ix":7},"sk":{"a":0,"k":0,"ix":4},"sa":{"a":0,"k":0,"ix":5},"nm":"Transformar"}],"nm":"Grupo 20","np":2,"cix":2,"bm":0,"ix":20,"mn":"ADBE Vector Group","hd":false},{"ty":"gr","it":[{"ind":0,"ty":"sh","ix":1,"ks":{"a":0,"k":{"i":[[0.102,-36.46],[0,0],[0,0],[0,0],[30.759,0]],"o":[[0,0],[0,0],[0,0],[-0.102,-36.48],[-30.776,0]],"v":[[-55.503,32.991],[-54.436,30.095],[-46.555,33.011],[55.503,23.312],[0.321,-33.011]],"c":true},"ix":2},"nm":"Trazado 1","mn":"ADBE Vector Shape - Group","hd":false},{"ty":"fl","c":{"a":0,"k":[0.180000005984,0.195999998205,0.20800000359,1],"ix":4},"o":{"a":0,"k":100,"ix":5},"r":1,"bm":0,"nm":"Relleno 1","mn":"ADBE Vector Graphic - Fill","hd":false},{"ty":"tr","p":{"a":0,"k":[446.669,288.843],"ix":2},"a":{"a":0,"k":[0,0],"ix":1},"s":{"a":0,"k":[100,100],"ix":3},"r":{"a":0,"k":0,"ix":6},"o":{"a":0,"k":100,"ix":7},"sk":{"a":0,"k":0,"ix":4},"sa":{"a":0,"k":0,"ix":5},"nm":"Transformar"}],"nm":"Grupo 21","np":2,"cix":2,"bm":0,"ix":21,"mn":"ADBE Vector Group","hd":false},{"ty":"gr","it":[{"ind":0,"ty":"sh","ix":1,"ks":{"a":0,"k":{"i":[[0,-29.104],[0.144,-1.552],[0,0],[0,0],[3.904,0.512],[0,3.872],[-29.104,0]],"o":[[0,1.584],[0,0],[0,0],[0,0],[-0.8,-3.632],[0,-29.104],[29.104,0]],"v":[[52.704,20.392],[52.496,25.112],[42.05,26.645],[-44.864,32.312],[-51.488,31.672],[-52.704,20.392],[0,-32.312]],"c":true},"ix":2},"nm":"Trazado 1","mn":"ADBE Vector Shape - Group","hd":false},{"ty":"fl","c":{"a":0,"k":[0.180000005984,0.195999998205,0.20800000359,1],"ix":4},"o":{"a":0,"k":100,"ix":5},"r":1,"bm":0,"nm":"Relleno 1","mn":"ADBE Vector Graphic - Fill","hd":false},{"ty":"tr","p":{"a":0,"k":[123.632,295.209],"ix":2},"a":{"a":0,"k":[0,0],"ix":1},"s":{"a":0,"k":[100,100],"ix":3},"r":{"a":0,"k":0,"ix":6},"o":{"a":0,"k":100,"ix":7},"sk":{"a":0,"k":0,"ix":4},"sa":{"a":0,"k":0,"ix":5},"nm":"Transformar"}],"nm":"Grupo 22","np":2,"cix":2,"bm":0,"ix":22,"mn":"ADBE Vector Group","hd":false}],"ip":0,"op":420,"st":0,"bm":0},{"ddd":0,"ind":9,"ty":4,"nm":"nube 3 contornos","sr":1,"ks":{"o":{"a":1,"k":[{"i":{"x":[0.833],"y":[0.833]},"o":{"x":[0.167],"y":[0.167]},"t":12,"s":[0]},{"t":32,"s":[100]}],"ix":11},"r":{"a":0,"k":0,"ix":10},"p":{"a":1,"k":[{"i":{"x":0.833,"y":0.833},"o":{"x":0.167,"y":0.167},"t":11,"s":[272.5,92,0],"to":[41.5,0,0],"ti":[-41.5,0,0]},{"t":147,"s":[521.5,92,0]}],"ix":2},"a":{"a":0,"k":[-48,256,0],"ix":1},"s":{"a":0,"k":[34,34,100],"ix":6}},"ao":0,"shapes":[{"ty":"gr","it":[{"ind":0,"ty":"sh","ix":1,"ks":{"a":0,"k":{"i":[[0,53.021],[-7.185,16.183],[0,-32.224],[-0.024,-0.79],[5.446,0],[0,-28.843],[-28.834,0],[0,0]],"o":[[0,-18.847],[-29.585,8.267],[0,0.8],[-4.936,-1.547],[-28.835,0],[0,28.835],[0,0],[-45.391,-20.453]],"v":[[15.452,-33.086],[26.637,-86.026],[-24.658,-18.4],[-24.6,-16.017],[-40.232,-18.4],[-92.445,33.817],[-40.232,86.026],[92.444,86.026]],"c":true},"ix":2},"nm":"Trazado 1","mn":"ADBE Vector Shape - Group","hd":false},{"ty":"fl","c":{"a":0,"k":[0.842999985639,0.929000016755,0.976000019148,1],"ix":4},"o":{"a":0,"k":100,"ix":5},"r":1,"bm":0,"nm":"Relleno 1","mn":"ADBE Vector Graphic - Fill","hd":false},{"ty":"tr","p":{"a":0,"k":[196.944,257.298],"ix":2},"a":{"a":0,"k":[0,0],"ix":1},"s":{"a":0,"k":[100,100],"ix":3},"r":{"a":0,"k":0,"ix":6},"o":{"a":0,"k":100,"ix":7},"sk":{"a":0,"k":0,"ix":4},"sa":{"a":0,"k":0,"ix":5},"nm":"Transformar"}],"nm":"Grupo 1","np":2,"cix":2,"bm":0,"ix":1,"mn":"ADBE Vector Group","hd":false},{"ty":"gr","it":[{"ind":0,"ty":"sh","ix":1,"ks":{"a":0,"k":{"i":[[29.175,0],[4.243,-1.1],[14.368,0],[4.197,-1.401],[33.443,0],[0,-38.787],[-0.024,-0.79],[5.446,0],[0,-28.843],[-28.834,0],[0,0],[0,0],[0,0],[0,29.173]],"o":[[-4.588,0],[-7.604,-10.982],[-4.668,0],[-7.074,-31.305],[-38.786,0],[0,0.8],[-4.936,-1.547],[-28.835,0],[0,28.835],[0,0],[0,0],[0,0],[29.175,0],[-0.002,-29.175]],"v":[[107.477,-18.32],[94.193,-16.632],[59.538,-34.807],[46.192,-32.637],[-22.291,-87.328],[-92.519,-17.098],[-92.46,-14.716],[-108.093,-17.098],[-160.305,35.118],[-108.093,87.328],[48.236,87.328],[77.248,87.328],[107.479,87.328],[160.306,34.504]],"c":true},"ix":2},"nm":"Trazado 1","mn":"ADBE Vector Shape - Group","hd":false},{"ty":"fl","c":{"a":0,"k":[0.894000004787,0.948999980852,0.976000019148,1],"ix":4},"o":{"a":0,"k":100,"ix":5},"r":1,"bm":0,"nm":"Relleno 1","mn":"ADBE Vector Graphic - Fill","hd":false},{"ty":"tr","p":{"a":0,"k":[264.808,255.999],"ix":2},"a":{"a":0,"k":[0,0],"ix":1},"s":{"a":0,"k":[100,100],"ix":3},"r":{"a":0,"k":0,"ix":6},"o":{"a":0,"k":100,"ix":7},"sk":{"a":0,"k":0,"ix":4},"sa":{"a":0,"k":0,"ix":5},"nm":"Transformar"}],"nm":"Grupo 2","np":2,"cix":2,"bm":0,"ix":2,"mn":"ADBE Vector Group","hd":false}],"ip":0,"op":420,"st":0,"bm":0},{"ddd":0,"ind":11,"ty":4,"nm":"nube 1 contornos","sr":1,"ks":{"o":{"a":1,"k":[{"i":{"x":[0.833],"y":[0.833]},"o":{"x":[0.167],"y":[0.167]},"t":-1,"s":[0]},{"t":31,"s":[100]}],"ix":11},"r":{"a":0,"k":0,"ix":10},"p":{"a":1,"k":[{"i":{"x":0.833,"y":0.833},"o":{"x":0.167,"y":0.167},"t":-1,"s":[101.49999999999999,59,0],"to":[76.667,0,0],"ti":[-76.667,0,0]},{"t":231,"s":[561.5,59,0]}],"ix":2},"a":{"a":0,"k":[256,256,0],"ix":1},"s":{"a":0,"k":[24,24,100],"ix":6}},"ao":0,"shapes":[{"ty":"gr","it":[{"ind":0,"ty":"sh","ix":1,"ks":{"a":0,"k":{"i":[[0,53.02],[-7.186,16.182],[0,-32.224],[-0.024,-0.79],[5.446,0],[0,-28.842],[-28.834,0],[0,0]],"o":[[0,-18.848],[-29.585,8.266],[0,0.799],[-4.936,-1.546],[-28.835,0],[0,28.835],[0,0],[-45.39,-20.453]],"v":[[15.452,-33.085],[26.637,-86.026],[-24.658,-18.399],[-24.6,-16.018],[-40.232,-18.399],[-92.445,33.816],[-40.232,86.026],[92.444,86.026]],"c":true},"ix":2},"nm":"Trazado 1","mn":"ADBE Vector Shape - Group","hd":false},{"ty":"fl","c":{"a":0,"k":[0.842999985639,0.929000016755,0.976000019148,1],"ix":4},"o":{"a":0,"k":100,"ix":5},"r":1,"bm":0,"nm":"Relleno 1","mn":"ADBE Vector Graphic - Fill","hd":false},{"ty":"tr","p":{"a":0,"k":[269.806,370.61],"ix":2},"a":{"a":0,"k":[0,0],"ix":1},"s":{"a":0,"k":[100,100],"ix":3},"r":{"a":0,"k":0,"ix":6},"o":{"a":0,"k":100,"ix":7},"sk":{"a":0,"k":0,"ix":4},"sa":{"a":0,"k":0,"ix":5},"nm":"Transformar"}],"nm":"Grupo 1","np":2,"cix":2,"bm":0,"ix":1,"mn":"ADBE Vector Group","hd":false},{"ty":"gr","it":[{"ind":0,"ty":"sh","ix":1,"ks":{"a":0,"k":{"i":[[29.175,0],[4.243,-1.099],[14.368,0],[4.196,-1.401],[33.444,0],[0,-38.787],[-0.024,-0.791],[5.445,0],[0,-28.843],[-28.834,0],[0,0],[0,0],[0,0],[0,29.173]],"o":[[-4.589,0],[-7.605,-10.981],[-4.668,0],[-7.074,-31.305],[-38.786,0],[0,0.799],[-4.937,-1.547],[-28.835,0],[0,28.834],[0,0],[0,0],[0,0],[29.175,0],[-0.002,-29.176]],"v":[[107.478,-18.319],[94.193,-16.632],[59.538,-34.806],[46.193,-32.636],[-22.292,-87.327],[-92.519,-17.097],[-92.459,-14.715],[-108.092,-17.097],[-160.305,35.119],[-108.092,87.328],[48.236,87.328],[77.249,87.328],[107.479,87.328],[160.305,34.505]],"c":true},"ix":2},"nm":"Trazado 1","mn":"ADBE Vector Shape - Group","hd":false},{"ty":"fl","c":{"a":0,"k":[0.894000004787,0.948999980852,0.976000019148,1],"ix":4},"o":{"a":0,"k":100,"ix":5},"r":1,"bm":0,"nm":"Relleno 1","mn":"ADBE Vector Graphic - Fill","hd":false},{"ty":"tr","p":{"a":0,"k":[337.669,369.311],"ix":2},"a":{"a":0,"k":[0,0],"ix":1},"s":{"a":0,"k":[100,100],"ix":3},"r":{"a":0,"k":0,"ix":6},"o":{"a":0,"k":100,"ix":7},"sk":{"a":0,"k":0,"ix":4},"sa":{"a":0,"k":0,"ix":5},"nm":"Transformar"}],"nm":"Grupo 2","np":2,"cix":2,"bm":0,"ix":2,"mn":"ADBE Vector Group","hd":false},{"ty":"gr","it":[{"ind":0,"ty":"sh","ix":1,"ks":{"a":0,"k":{"i":[[14.519,58.015],[1.708,0],[0,-46.591],[-46.59,0],[0,0],[-4.064,7.369]],"o":[[-1.682,-0.102],[-46.59,-0.001],[0,46.588],[0,0],[0.061,-8.999],[-45.989,-35.392]],"v":[[-2.475,-84.202],[-7.559,-84.359],[-91.917,-0.001],[-7.559,84.36],[85.452,84.36],[91.916,59.536]],"c":true},"ix":2},"nm":"Trazado 1","mn":"ADBE Vector Shape - Group","hd":false},{"ty":"fl","c":{"a":0,"k":[0.681999954523,0.894000004787,1,1],"ix":4},"o":{"a":0,"k":100,"ix":5},"r":1,"bm":0,"nm":"Relleno 1","mn":"ADBE Vector Graphic - Fill","hd":false},{"ty":"tr","p":{"a":0,"k":[91.916,321.942],"ix":2},"a":{"a":0,"k":[0,0],"ix":1},"s":{"a":0,"k":[100,100],"ix":3},"r":{"a":0,"k":0,"ix":6},"o":{"a":0,"k":100,"ix":7},"sk":{"a":0,"k":0,"ix":4},"sa":{"a":0,"k":0,"ix":5},"nm":"Transformar"}],"nm":"Grupo 3","np":4,"cix":2,"bm":0,"ix":3,"mn":"ADBE Vector Group","hd":false},{"ty":"gr","it":[{"ind":0,"ty":"sh","ix":1,"ks":{"a":0,"k":{"i":[[0,0],[32.334,0],[11.296,-49.995],[7.453,0],[12.145,-17.532],[7.328,0],[0,-46.59],[-46.59,0],[0,0],[-28.717,0],[-4.936,-1.547],[0,0.8],[-38.786,0],[-7.073,-31.304],[-4.668,0],[-7.604,-10.981],[-4.587,0],[-9.238,-15.358],[0,21.526],[46.052,0],[7.883,-2.47],[0,1.274],[8.204,15.584]],"o":[[-20.468,-21.893],[-53.408,0],[-6.704,-2.236],[-22.947,0],[-6.779,-1.751],[-46.59,0],[0,46.588],[0,0],[0.196,-28.675],[5.446,0],[-0.023,-0.79],[0,-38.787],[33.443,0],[4.197,-1.401],[14.368,0],[4.245,-1.099],[19.232,0],[13.396,-14.793],[0,-46.056],[-8.696,0],[0.041,-1.263],[0,-18.832],[0,0]],"v":[[117.538,-103.884],[35.596,-139.461],[-73.765,-52.121],[-95.083,-55.587],[-150.424,-26.565],[-171.641,-29.258],[-255.999,55.1],[-171.641,139.461],[-78.63,139.461],[-26.423,87.603],[-10.79,89.985],[-10.849,87.603],[59.378,17.373],[127.861,72.064],[141.207,69.894],[175.862,88.069],[189.146,86.381],[234.441,112.018],[255.999,56.078],[172.615,-27.306],[147.651,-23.503],[147.747,-27.306],[134.902,-79.469]],"c":false},"ix":2},"nm":"Trazado 1","mn":"ADBE Vector Shape - Group","hd":false},{"ty":"fl","c":{"a":0,"k":[0.745000023935,0.917999985639,0.987999949736,1],"ix":4},"o":{"a":0,"k":100,"ix":5},"r":1,"bm":0,"nm":"Relleno 1","mn":"ADBE Vector Graphic - Fill","hd":false},{"ty":"tr","p":{"a":0,"k":[255.999,266.841],"ix":2},"a":{"a":0,"k":[0,0],"ix":1},"s":{"a":0,"k":[100,100],"ix":3},"r":{"a":0,"k":0,"ix":6},"o":{"a":0,"k":100,"ix":7},"sk":{"a":0,"k":0,"ix":4},"sa":{"a":0,"k":0,"ix":5},"nm":"Transformar"}],"nm":"Grupo 4","np":2,"cix":2,"bm":0,"ix":4,"mn":"ADBE Vector Group","hd":false}],"ip":0,"op":420,"st":0,"bm":0},{"ddd":0,"ind":13,"ty":4,"nm":"nube 1 contornos","sr":1,"ks":{"o":{"a":1,"k":[{"i":{"x":[0.833],"y":[0.833]},"o":{"x":[0.167],"y":[0.167]},"t":54,"s":[0]},{"t":87,"s":[100]}],"ix":11},"r":{"a":0,"k":0,"ix":10},"p":{"a":1,"k":[{"i":{"x":0.833,"y":0.833},"o":{"x":0.167,"y":0.167},"t":54,"s":[-38.5,84,0],"to":[96,0,0],"ti":[-96,0,0]},{"t":415,"s":[537.5,84,0]}],"ix":2},"a":{"a":0,"k":[256,256,0],"ix":1},"s":{"a":0,"k":[12,12,100],"ix":6}},"ao":0,"shapes":[{"ty":"gr","it":[{"ind":0,"ty":"sh","ix":1,"ks":{"a":0,"k":{"i":[[0,53.02],[-7.186,16.182],[0,-32.224],[-0.024,-0.79],[5.446,0],[0,-28.842],[-28.834,0],[0,0]],"o":[[0,-18.848],[-29.585,8.266],[0,0.799],[-4.936,-1.546],[-28.835,0],[0,28.835],[0,0],[-45.39,-20.453]],"v":[[15.452,-33.085],[26.637,-86.026],[-24.658,-18.399],[-24.6,-16.018],[-40.232,-18.399],[-92.445,33.816],[-40.232,86.026],[92.444,86.026]],"c":true},"ix":2},"nm":"Trazado 1","mn":"ADBE Vector Shape - Group","hd":false},{"ty":"fl","c":{"a":0,"k":[0.842999985639,0.929000016755,0.976000019148,1],"ix":4},"o":{"a":0,"k":100,"ix":5},"r":1,"bm":0,"nm":"Relleno 1","mn":"ADBE Vector Graphic - Fill","hd":false},{"ty":"tr","p":{"a":0,"k":[269.806,370.61],"ix":2},"a":{"a":0,"k":[0,0],"ix":1},"s":{"a":0,"k":[100,100],"ix":3},"r":{"a":0,"k":0,"ix":6},"o":{"a":0,"k":100,"ix":7},"sk":{"a":0,"k":0,"ix":4},"sa":{"a":0,"k":0,"ix":5},"nm":"Transformar"}],"nm":"Grupo 1","np":2,"cix":2,"bm":0,"ix":1,"mn":"ADBE Vector Group","hd":false},{"ty":"gr","it":[{"ind":0,"ty":"sh","ix":1,"ks":{"a":0,"k":{"i":[[29.175,0],[4.243,-1.099],[14.368,0],[4.196,-1.401],[33.444,0],[0,-38.787],[-0.024,-0.791],[5.445,0],[0,-28.843],[-28.834,0],[0,0],[0,0],[0,0],[0,29.173]],"o":[[-4.589,0],[-7.605,-10.981],[-4.668,0],[-7.074,-31.305],[-38.786,0],[0,0.799],[-4.937,-1.547],[-28.835,0],[0,28.834],[0,0],[0,0],[0,0],[29.175,0],[-0.002,-29.176]],"v":[[107.478,-18.319],[94.193,-16.632],[59.538,-34.806],[46.193,-32.636],[-22.292,-87.327],[-92.519,-17.097],[-92.459,-14.715],[-108.092,-17.097],[-160.305,35.119],[-108.092,87.328],[48.236,87.328],[77.249,87.328],[107.479,87.328],[160.305,34.505]],"c":true},"ix":2},"nm":"Trazado 1","mn":"ADBE Vector Shape - Group","hd":false},{"ty":"fl","c":{"a":0,"k":[0.894000004787,0.948999980852,0.976000019148,1],"ix":4},"o":{"a":0,"k":100,"ix":5},"r":1,"bm":0,"nm":"Relleno 1","mn":"ADBE Vector Graphic - Fill","hd":false},{"ty":"tr","p":{"a":0,"k":[337.669,369.311],"ix":2},"a":{"a":0,"k":[0,0],"ix":1},"s":{"a":0,"k":[100,100],"ix":3},"r":{"a":0,"k":0,"ix":6},"o":{"a":0,"k":100,"ix":7},"sk":{"a":0,"k":0,"ix":4},"sa":{"a":0,"k":0,"ix":5},"nm":"Transformar"}],"nm":"Grupo 2","np":2,"cix":2,"bm":0,"ix":2,"mn":"ADBE Vector Group","hd":false},{"ty":"gr","it":[{"ind":0,"ty":"sh","ix":1,"ks":{"a":0,"k":{"i":[[14.519,58.015],[1.708,0],[0,-46.591],[-46.59,0],[0,0],[-4.064,7.369]],"o":[[-1.682,-0.102],[-46.59,-0.001],[0,46.588],[0,0],[0.061,-8.999],[-45.989,-35.392]],"v":[[-2.475,-84.202],[-7.559,-84.359],[-91.917,-0.001],[-7.559,84.36],[85.452,84.36],[91.916,59.536]],"c":true},"ix":2},"nm":"Trazado 1","mn":"ADBE Vector Shape - Group","hd":false},{"ty":"fl","c":{"a":0,"k":[0.681999954523,0.894000004787,1,1],"ix":4},"o":{"a":0,"k":100,"ix":5},"r":1,"bm":0,"nm":"Relleno 1","mn":"ADBE Vector Graphic - Fill","hd":false},{"ty":"tr","p":{"a":0,"k":[91.916,321.942],"ix":2},"a":{"a":0,"k":[0,0],"ix":1},"s":{"a":0,"k":[100,100],"ix":3},"r":{"a":0,"k":0,"ix":6},"o":{"a":0,"k":100,"ix":7},"sk":{"a":0,"k":0,"ix":4},"sa":{"a":0,"k":0,"ix":5},"nm":"Transformar"}],"nm":"Grupo 3","np":4,"cix":2,"bm":0,"ix":3,"mn":"ADBE Vector Group","hd":false},{"ty":"gr","it":[{"ind":0,"ty":"sh","ix":1,"ks":{"a":0,"k":{"i":[[0,0],[32.334,0],[11.296,-49.995],[7.453,0],[12.145,-17.532],[7.328,0],[0,-46.59],[-46.59,0],[0,0],[-28.717,0],[-4.936,-1.547],[0,0.8],[-38.786,0],[-7.073,-31.304],[-4.668,0],[-7.604,-10.981],[-4.587,0],[-9.238,-15.358],[0,21.526],[46.052,0],[7.883,-2.47],[0,1.274],[8.204,15.584]],"o":[[-20.468,-21.893],[-53.408,0],[-6.704,-2.236],[-22.947,0],[-6.779,-1.751],[-46.59,0],[0,46.588],[0,0],[0.196,-28.675],[5.446,0],[-0.023,-0.79],[0,-38.787],[33.443,0],[4.197,-1.401],[14.368,0],[4.245,-1.099],[19.232,0],[13.396,-14.793],[0,-46.056],[-8.696,0],[0.041,-1.263],[0,-18.832],[0,0]],"v":[[117.538,-103.884],[35.596,-139.461],[-73.765,-52.121],[-95.083,-55.587],[-150.424,-26.565],[-171.641,-29.258],[-255.999,55.1],[-171.641,139.461],[-78.63,139.461],[-26.423,87.603],[-10.79,89.985],[-10.849,87.603],[59.378,17.373],[127.861,72.064],[141.207,69.894],[175.862,88.069],[189.146,86.381],[234.441,112.018],[255.999,56.078],[172.615,-27.306],[147.651,-23.503],[147.747,-27.306],[134.902,-79.469]],"c":false},"ix":2},"nm":"Trazado 1","mn":"ADBE Vector Shape - Group","hd":false},{"ty":"fl","c":{"a":0,"k":[0.745000023935,0.917999985639,0.987999949736,1],"ix":4},"o":{"a":0,"k":100,"ix":5},"r":1,"bm":0,"nm":"Relleno 1","mn":"ADBE Vector Graphic - Fill","hd":false},{"ty":"tr","p":{"a":0,"k":[255.999,266.841],"ix":2},"a":{"a":0,"k":[0,0],"ix":1},"s":{"a":0,"k":[100,100],"ix":3},"r":{"a":0,"k":0,"ix":6},"o":{"a":0,"k":100,"ix":7},"sk":{"a":0,"k":0,"ix":4},"sa":{"a":0,"k":0,"ix":5},"nm":"Transformar"}],"nm":"Grupo 4","np":2,"cix":2,"bm":0,"ix":4,"mn":"ADBE Vector Group","hd":false}],"ip":0,"op":420,"st":0,"bm":0},{"ddd":0,"ind":15,"ty":4,"nm":"nube 3 contornos","sr":1,"ks":{"o":{"a":1,"k":[{"i":{"x":[0.833],"y":[0.833]},"o":{"x":[0.167],"y":[0.167]},"t":129,"s":[0]},{"t":149,"s":[100]}],"ix":11},"r":{"a":0,"k":0,"ix":10},"p":{"a":1,"k":[{"i":{"x":0.833,"y":0.833},"o":{"x":0.167,"y":0.167},"t":129,"s":[-153.553,127,0],"to":[0,0,0],"ti":[0,0,0]},{"t":467,"s":[459.447,127,0]}],"ix":2},"a":{"a":0,"k":[-48,256,0],"ix":1},"s":{"a":0,"k":[25,25,100],"ix":6}},"ao":0,"shapes":[{"ty":"gr","it":[{"ind":0,"ty":"sh","ix":1,"ks":{"a":0,"k":{"i":[[0,53.021],[-7.185,16.183],[0,-32.224],[-0.024,-0.79],[5.446,0],[0,-28.843],[-28.834,0],[0,0]],"o":[[0,-18.847],[-29.585,8.267],[0,0.8],[-4.936,-1.547],[-28.835,0],[0,28.835],[0,0],[-45.391,-20.453]],"v":[[15.452,-33.086],[26.637,-86.026],[-24.658,-18.4],[-24.6,-16.017],[-40.232,-18.4],[-92.445,33.817],[-40.232,86.026],[92.444,86.026]],"c":true},"ix":2},"nm":"Trazado 1","mn":"ADBE Vector Shape - Group","hd":false},{"ty":"fl","c":{"a":0,"k":[0.842999985639,0.929000016755,0.976000019148,1],"ix":4},"o":{"a":0,"k":100,"ix":5},"r":1,"bm":0,"nm":"Relleno 1","mn":"ADBE Vector Graphic - Fill","hd":false},{"ty":"tr","p":{"a":0,"k":[196.944,257.298],"ix":2},"a":{"a":0,"k":[0,0],"ix":1},"s":{"a":0,"k":[100,100],"ix":3},"r":{"a":0,"k":0,"ix":6},"o":{"a":0,"k":100,"ix":7},"sk":{"a":0,"k":0,"ix":4},"sa":{"a":0,"k":0,"ix":5},"nm":"Transformar"}],"nm":"Grupo 1","np":2,"cix":2,"bm":0,"ix":1,"mn":"ADBE Vector Group","hd":false},{"ty":"gr","it":[{"ind":0,"ty":"sh","ix":1,"ks":{"a":0,"k":{"i":[[29.175,0],[4.243,-1.1],[14.368,0],[4.197,-1.401],[33.443,0],[0,-38.787],[-0.024,-0.79],[5.446,0],[0,-28.843],[-28.834,0],[0,0],[0,0],[0,0],[0,29.173]],"o":[[-4.588,0],[-7.604,-10.982],[-4.668,0],[-7.074,-31.305],[-38.786,0],[0,0.8],[-4.936,-1.547],[-28.835,0],[0,28.835],[0,0],[0,0],[0,0],[29.175,0],[-0.002,-29.175]],"v":[[107.477,-18.32],[94.193,-16.632],[59.538,-34.807],[46.192,-32.637],[-22.291,-87.328],[-92.519,-17.098],[-92.46,-14.716],[-108.093,-17.098],[-160.305,35.118],[-108.093,87.328],[48.236,87.328],[77.248,87.328],[107.479,87.328],[160.306,34.504]],"c":true},"ix":2},"nm":"Trazado 1","mn":"ADBE Vector Shape - Group","hd":false},{"ty":"fl","c":{"a":0,"k":[0.894000004787,0.948999980852,0.976000019148,1],"ix":4},"o":{"a":0,"k":100,"ix":5},"r":1,"bm":0,"nm":"Relleno 1","mn":"ADBE Vector Graphic - Fill","hd":false},{"ty":"tr","p":{"a":0,"k":[264.808,255.999],"ix":2},"a":{"a":0,"k":[0,0],"ix":1},"s":{"a":0,"k":[100,100],"ix":3},"r":{"a":0,"k":0,"ix":6},"o":{"a":0,"k":100,"ix":7},"sk":{"a":0,"k":0,"ix":4},"sa":{"a":0,"k":0,"ix":5},"nm":"Transformar"}],"nm":"Grupo 2","np":2,"cix":2,"bm":0,"ix":2,"mn":"ADBE Vector Group","hd":false}],"ip":0,"op":420,"st":0,"bm":0}],"markers":[]}